llama_index/readers/azure_devops/BUILD
llama_index/readers/azure_devops/__init__.py
llama_index/readers/azure_devops/base.py
llama_index_readers_azure_devops-0.3.0.dist-info/METADATA
llama_index_readers_azure_devops-0.3.0.dist-info/WHEEL
llama_index_readers_azure_devops-0.3.0.dist-info/RECORD
