Metadata-Version: 2.1
Name: llama-index-readers-azure-devops
Version: 0.3.0
Summary: llama-index readers azure devops integration
License: MIT
Author: Your Name
Author-email: you@example.com
Requires-Python: >=3.9,<4.0
Classifier: License :: OSI Approved :: MIT License
Classifier: Programming Language :: Python :: 3
Classifier: Programming Language :: Python :: 3.9
Classifier: Programming Language :: Python :: 3.10
Classifier: Programming Language :: Python :: 3.11
Classifier: Programming Language :: Python :: 3.12
Requires-Dist: azure-devops (==7.1.0b4)
Requires-Dist: llama-index-core (>=0.12.0,<0.13.0)
